neupi/__init__.py
neupi/losses.py
neupi/registry.py
neupi/core/discretizer.py
neupi/core/embedding.py
neupi/core/inference_module.py
neupi/core/model.py
neupi/core/trainer.py
neupi/discretize/__init__.py
neupi/discretize/kn.py
neupi/discretize/oauai.py
neupi/discretize/threshold.py
neupi/discretize/cython_kn/kn_binary_vectors.cpp
neupi/discretize/cython_kn/kn_binary_vectors.cpython-38-x86_64-linux-gnu.so
neupi/discretize/cython_kn/kn_binary_vectors.pyx
neupi/embedding/__init__.py
neupi/embedding/discrete.py
neupi/embedding/identity.py
neupi/inference/__init__.py
neupi/inference/itself.py
neupi/inference/single_pass.py
neupi/models/__init__.py
neupi/models/nn.py
neupi/training/pm_ssl/__init__.py
neupi/training/pm_ssl/io/uai_reader_cython.cpp
neupi/training/pm_ssl/io/uai_reader_cython.cpython-38-x86_64-linux-gnu.so
neupi/training/pm_ssl/io/uai_reader_cython.pyx
neupi/training/pm_ssl/nam/made.py
neupi/training/pm_ssl/pc/spn.py
neupi/training/pm_ssl/pc/spn_utils/__init__.py
neupi/training/pm_ssl/pc/spn_utils/spn_node_classes.py
neupi/training/pm_ssl/pc/spn_utils/spn_utils.py
neupi/training/pm_ssl/pgm/mn.py
neupi/training/trainers/__init__.py
neupi/training/trainers/ssl_trainer.py
neupi/utils/__init__.py
neupi/utils/pgm_utils.py
neupi.libs/libgomp-a34b3233.so.1.0.0
neupi-1.1.0.dist-info/LICENSE
neupi-1.1.0.dist-info/METADATA
neupi-1.1.0.dist-info/WHEEL
neupi-1.1.0.dist-info/top_level.txt
neupi-1.1.0.dist-info/RECORD
