Metadata-Version: 2.1
Name: neupi
Version: 1.1.0
Summary: A library of neural solvers for fast and accurate inference over Probabilistic Models.
Author-email: Shivvrat Arya <shivvrat.arya@utdallas.edu>
Project-URL: Homepage, https://github.com/Shivvrat/NeuPI
Project-URL: Issues, https://github.com/Shivvrat/NeuPI/issues
Classifier: Programming Language :: Python :: 3
Classifier: License :: OSI Approved :: MIT License
Classifier: Operating System :: POSIX :: Linux
Classifier: Intended Audience :: Science/Research
Classifier: Topic :: Scientific/Engineering :: Artificial Intelligence
Requires-Python: >=3.8
License-File: LICENSE
Requires-Dist: numpy>=1.24
Requires-Dist: torch>=2.3.0
Requires-Dist: cython>=3.0.11
Requires-Dist: setuptools>=70.0
Provides-Extra: docs
Requires-Dist: sphinx; extra == "docs"
Requires-Dist: furo; extra == "docs"
Requires-Dist: myst-parser; extra == "docs"
Provides-Extra: gpu
